Metadata-Version: 2.4
Name: urllib3-lts-py38
Version: 2025.66471.2
Summary: Python 3.8 urllib3 with CVE-2025-66471 security patches
Author-email: 1minds3t <1minds3t@proton.me>
License: MIT
Project-URL: Homepage, https://github.com/1minds3t/urllib3-lts
Project-URL: Source, https://github.com/1minds3t/urllib3-lts/tree/py38
Classifier: Programming Language :: Python :: 3.8
Classifier: Topic :: Security
Classifier: Intended Audience :: Developers
Requires-Python: <3.9,>=3.8
License-File: LICENSE.txt
Dynamic: license-file
